exelock/__init__.py
exelock/core.py
exelock-1.0.2.dist-info/METADATA
exelock-1.0.2.dist-info/WHEEL
exelock-1.0.2.dist-info/top_level.txt
exelock-1.0.2.dist-info/RECORD
